{
  "asin": "B0BYS7VHMN",
  "url": "https://www.amazon.com/dp/B0BYS7VHMN",
  "title": "LOVEVOOK Laptop Tote Bag for Women, 15.6 Inch Large Capacity Vintage Leather Work Computer Bag, Business Casual Shoulder Handbag, Dark Brown",
  "price": "59,458",
  "images": [
    "https://images-na.ssl-images-amazon.com/images/I/717E224UCWL._AC_UL116_SR116,116_.jpg",
    "https://images-na.ssl-images-amazon.com/images/I/717E224UCWL._AC_UL232_SR232,232_.jpg",
    "https://images-na.ssl-images-amazon.com/images/I/717E224UCWL._AC_UL348_SR348,348_.jpg",
    "https://images-na.ssl-images-amazon.com/images/I/51dsuumz6HL._AC_UL116_SR116,116_.jpg",
    "https://images-na.ssl-images-amazon.com/images/I/51dsuumz6HL._AC_UL232_SR232,232_.jpg",
    "https://images-na.ssl-images-amazon.com/images/I/51dsuumz6HL._AC_UL348_SR348,348_.jpg",
    "https://images-na.ssl-images-amazon.com/images/I/81atQ6BlaBL._AC_UL165_SR165,165_.jpg",
    "https://images-na.ssl-images-amazon.com/images/I/81atQ6BlaBL._AC_UL330_SR330,330_.jpg",
    "https://images-na.ssl-images-amazon.com/images/I/81atQ6BlaBL._AC_UL495_SR495,495_.jpg",
    "https://images-na.ssl-images-amazon.com/images/I/71vCtGO3K4L._AC_UL165_SR165,165_.jpg",
    "https://images-na.ssl-images-amazon.com/images/I/71vCtGO3K4L._AC_UL330_SR330,330_.jpg",
    "https://images-na.ssl-images-amazon.com/images/I/71vCtGO3K4L._AC_UL495_SR495,495_.jpg",
    "https://images-na.ssl-images-amazon.com/images/I/71X4jB5V-8L._AC_UL165_SR165,165_.jpg",
    "https://images-na.ssl-images-amazon.com/images/I/71X4jB5V-8L._AC_UL330_SR330,330_.jpg",
    "https://images-na.ssl-images-amazon.com/images/I/71X4jB5V-8L._AC_UL495_SR495,495_.jpg",
    "https://images-na.ssl-images-amazon.com/images/I/61Oo+cVhFeL._AC_UL165_SR165,165_.jpg",
    "https://images-na.ssl-images-amazon.com/images/I/61Oo+cVhFeL._AC_UL330_SR330,330_.jpg",
    "https://images-na.ssl-images-amazon.com/images/I/61Oo+cVhFeL._AC_UL495_SR495,495_.jpg",
    "https://images-na.ssl-images-amazon.com/images/I/713XvMGfHJL._AC_UL165_SR165,165_.jpg",
    "https://images-na.ssl-images-amazon.com/images/I/713XvMGfHJL._AC_UL330_SR330,330_.jpg",
    "https://images-na.ssl-images-amazon.com/images/I/713XvMGfHJL._AC_UL495_SR495,495_.jpg",
    "https://images-na.ssl-images-amazon.com/images/I/71Gue3O3vJL._AC_UL165_SR165,165_.jpg",
    "https://images-na.ssl-images-amazon.com/images/I/71Gue3O3vJL._AC_UL330_SR330,330_.jpg",
    "https://images-na.ssl-images-amazon.com/images/I/71Gue3O3vJL._AC_UL495_SR495,495_.jpg"
  ],
  "video_urls": [
    "https://m.media-amazon.com/images/S/vse-vms-transcoding-artifact-us-east-1-prod/0ade8d23-11e7-4b55-9e81-1f2b0be670a3/default.vertical.jobtemplate.hls.m3u8",
    "https://m.media-amazon.com/images/S/vse-vms-transcoding-artifact-us-east-1-prod/a3132a8f-76b7-4ecd-8692-b24aa1d8b6b9/default.jobtemplate.hls.m3u8",
    "https://m.media-amazon.com/images/S/vse-vms-transcoding-artifact-us-east-1-prod/db079546-a1ac-4eff-992a-7e355aa9c560/default.jobtemplate.hls.m3u8",
    "https://m.media-amazon.com/images/S/vse-vms-transcoding-artifact-us-east-1-prod/b7f78ffc-e4be-4a7a-b41f-78dd4907dcef/default.jobtemplate.hls.m3u8",
    "https://m.media-amazon.com/images/S/vse-vms-transcoding-artifact-us-east-1-prod/4ee481cd-39a8-4437-84a7-6adc4e9eedc5/default.vertical.jobtemplate.hls.m3u8",
    "https://m.media-amazon.com/images/S/vse-vms-transcoding-artifact-us-east-1-prod/fe59e1de-c9b1-4c24-9045-08f52f423e89/default.vertical.jobtemplate.hls.m3u8",
    "https://m.media-amazon.com/images/S/vse-vms-transcoding-artifact-us-east-1-prod/8f851b84-e582-4935-90bf-6742c8ddca8d/default.jobtemplate.hls.m3u8",
    "https://m.media-amazon.com/images/S/vse-vms-transcoding-artifact-us-east-1-prod/958e6e40-8351-4496-ab44-502387a1edd0/default.vertical.jobtemplate.hls.m3u8"
  ],
  "platform": "amazon",
  "category": "handbag",
  "keyword": "women tote handbag",
  "scraped_at": "2026-03-10T00:16:41.199959",
  "download_stats": {
    "images_downloaded": 8,
    "videos_downloaded": 7,
    "images_skipped": 0
  }
}