{
  "asin": "B086PMT54H",
  "url": "https://www.amazon.com/dp/B086PMT54H",
  "title": "XYJZXY Gold Huggie Small Hoop Earrings with Charm Personalized Snake/Evil Eye/Star/Cross/Lock/Key 18k Gold Plated Crystal Drop Dangle Earrings for Women",
  "price": "21,607",
  "images": [
    "https://images-na.ssl-images-amazon.com/images/I/51vKS8YZSGL._AC_UL116_SR116,116_.jpg",
    "https://images-na.ssl-images-amazon.com/images/I/51vKS8YZSGL._AC_UL232_SR232,232_.jpg",
    "https://images-na.ssl-images-amazon.com/images/I/51vKS8YZSGL._AC_UL348_SR348,348_.jpg",
    "https://images-na.ssl-images-amazon.com/images/I/51fL2v42pRL._AC_UL116_SR116,116_.jpg",
    "https://images-na.ssl-images-amazon.com/images/I/51fL2v42pRL._AC_UL232_SR232,232_.jpg",
    "https://images-na.ssl-images-amazon.com/images/I/51fL2v42pRL._AC_UL348_SR348,348_.jpg",
    "https://images-na.ssl-images-amazon.com/images/I/51pj-XdVaZL._AC_UL165_SR165,165_.jpg",
    "https://images-na.ssl-images-amazon.com/images/I/51pj-XdVaZL._AC_UL330_SR330,330_.jpg",
    "https://images-na.ssl-images-amazon.com/images/I/51pj-XdVaZL._AC_UL495_SR495,495_.jpg",
    "https://images-na.ssl-images-amazon.com/images/I/613s9xM6d7L._AC_UL165_SR165,165_.jpg",
    "https://images-na.ssl-images-amazon.com/images/I/613s9xM6d7L._AC_UL330_SR330,330_.jpg",
    "https://images-na.ssl-images-amazon.com/images/I/613s9xM6d7L._AC_UL495_SR495,495_.jpg",
    "https://images-na.ssl-images-amazon.com/images/I/613s6KQbmrL._AC_UL165_SR165,165_.jpg",
    "https://images-na.ssl-images-amazon.com/images/I/613s6KQbmrL._AC_UL330_SR330,330_.jpg",
    "https://images-na.ssl-images-amazon.com/images/I/613s6KQbmrL._AC_UL495_SR495,495_.jpg",
    "https://images-na.ssl-images-amazon.com/images/I/61hn-c0njjL._AC_UL165_SR165,165_.jpg",
    "https://images-na.ssl-images-amazon.com/images/I/61hn-c0njjL._AC_UL330_SR330,330_.jpg",
    "https://images-na.ssl-images-amazon.com/images/I/61hn-c0njjL._AC_UL495_SR495,495_.jpg",
    "https://images-na.ssl-images-amazon.com/images/I/515Wmo9YGAL._AC_UL165_SR165,165_.jpg",
    "https://images-na.ssl-images-amazon.com/images/I/515Wmo9YGAL._AC_UL330_SR330,330_.jpg",
    "https://images-na.ssl-images-amazon.com/images/I/515Wmo9YGAL._AC_UL495_SR495,495_.jpg",
    "https://images-na.ssl-images-amazon.com/images/I/51tthpFcAkL._AC_UL165_SR165,165_.jpg",
    "https://images-na.ssl-images-amazon.com/images/I/51tthpFcAkL._AC_UL330_SR330,330_.jpg",
    "https://images-na.ssl-images-amazon.com/images/I/51tthpFcAkL._AC_UL495_SR495,495_.jpg"
  ],
  "video_urls": [
    "https://m.media-amazon.com/images/S/vse-vms-transcoding-artifact-us-east-1-prod/67aeeeee-f486-48b1-a8c4-3a02986ee5e2/default.jobtemplate.hls.m3u8",
    "https://m.media-amazon.com/images/S/vse-vms-transcoding-artifact-us-east-1-prod/c7b1b680-e241-4e33-b351-b525fca5e703/default.jobtemplate.hls.m3u8"
  ],
  "platform": "amazon",
  "category": "earring",
  "keyword": "pearl earrings",
  "scraped_at": "2026-03-14T00:05:32.642775",
  "download_stats": {
    "images_downloaded": 8,
    "videos_downloaded": 2,
    "images_skipped": 0
  }
}