{
  "asin": "B0F21SQHTJ",
  "url": "https://www.amazon.com/dp/B0F21SQHTJ",
  "title": "LOLIAS Flat Back Earrings for Women Hypoallergenic Surgical Steel Earrings for Sensitive Ears-20G Cartilage Earring Stacks 14K Gold Plated Hoops Flatback Stud Earring Sets for Multiple Piercing",
  "price": "17.",
  "images": [
    "https://images-na.ssl-images-amazon.com/images/I/81YswHVjWCL._AC_UL116_SR116,116_.jpg",
    "https://images-na.ssl-images-amazon.com/images/I/81YswHVjWCL._AC_UL232_SR232,232_.jpg",
    "https://images-na.ssl-images-amazon.com/images/I/81YswHVjWCL._AC_UL348_SR348,348_.jpg",
    "https://images-na.ssl-images-amazon.com/images/I/71uZzNRbUcL._AC_UL116_SR116,116_.jpg",
    "https://images-na.ssl-images-amazon.com/images/I/71uZzNRbUcL._AC_UL232_SR232,232_.jpg",
    "https://images-na.ssl-images-amazon.com/images/I/71uZzNRbUcL._AC_UL348_SR348,348_.jpg",
    "https://images-na.ssl-images-amazon.com/images/I/51-DHLS52AL._AC_UL116_SR116,116_.jpg",
    "https://images-na.ssl-images-amazon.com/images/I/51-DHLS52AL._AC_UL232_SR232,232_.jpg",
    "https://images-na.ssl-images-amazon.com/images/I/51-DHLS52AL._AC_UL348_SR348,348_.jpg",
    "https://images-na.ssl-images-amazon.com/images/I/71r5OfkwXeL._AC_UL165_SR165,165_.jpg",
    "https://images-na.ssl-images-amazon.com/images/I/71r5OfkwXeL._AC_UL330_SR330,330_.jpg",
    "https://images-na.ssl-images-amazon.com/images/I/71r5OfkwXeL._AC_UL495_SR495,495_.jpg",
    "https://images-na.ssl-images-amazon.com/images/I/81KuSdErmxL._AC_UL165_SR165,165_.jpg",
    "https://images-na.ssl-images-amazon.com/images/I/81KuSdErmxL._AC_UL330_SR330,330_.jpg",
    "https://images-na.ssl-images-amazon.com/images/I/81KuSdErmxL._AC_UL495_SR495,495_.jpg",
    "https://images-na.ssl-images-amazon.com/images/I/71+38Dbe2SL._AC_UL165_SR165,165_.jpg",
    "https://images-na.ssl-images-amazon.com/images/I/71+38Dbe2SL._AC_UL330_SR330,330_.jpg",
    "https://images-na.ssl-images-amazon.com/images/I/71+38Dbe2SL._AC_UL495_SR495,495_.jpg",
    "https://images-na.ssl-images-amazon.com/images/I/71uJ7Q+w13L._AC_UL165_SR165,165_.jpg",
    "https://images-na.ssl-images-amazon.com/images/I/71uJ7Q+w13L._AC_UL330_SR330,330_.jpg",
    "https://images-na.ssl-images-amazon.com/images/I/71uJ7Q+w13L._AC_UL495_SR495,495_.jpg",
    "https://images-na.ssl-images-amazon.com/images/I/71UVPPjJ7rL._AC_UL165_SR165,165_.jpg",
    "https://images-na.ssl-images-amazon.com/images/I/71UVPPjJ7rL._AC_UL330_SR330,330_.jpg",
    "https://images-na.ssl-images-amazon.com/images/I/71UVPPjJ7rL._AC_UL495_SR495,495_.jpg",
    "https://images-na.ssl-images-amazon.com/images/I/715hNSO-n4L._AC_UL165_SR165,165_.jpg",
    "https://images-na.ssl-images-amazon.com/images/I/715hNSO-n4L._AC_UL330_SR330,330_.jpg",
    "https://images-na.ssl-images-amazon.com/images/I/715hNSO-n4L._AC_UL495_SR495,495_.jpg"
  ],
  "video_urls": [
    "https://m.media-amazon.com/images/S/vse-vms-transcoding-artifact-us-east-1-prod/d4804416-7d75-4ffa-8ce8-9bfac1dbaa1d/default.jobtemplate.hls.m3u8"
  ],
  "platform": "amazon",
  "category": "earring",
  "keyword": "stud earrings gold",
  "scraped_at": "2026-03-08T22:44:49.791437",
  "download_stats": {
    "images_downloaded": 8,
    "videos_downloaded": 1,
    "images_skipped": 0
  }
}