{
  "asin": "B07PJR85M8",
  "url": "https://www.amazon.com/dp/B07PJR85M8",
  "title": "Rainbow Moonstone Healing Crystal Necklace - Lunar Pendant Balance, Inner Light, Love & Creativity",
  "price": "19,240",
  "images": [
    "https://images-na.ssl-images-amazon.com/images/I/619rzmze5cL._AC_UL165_SR165,165_.jpg",
    "https://images-na.ssl-images-amazon.com/images/I/619rzmze5cL._AC_UL330_SR330,330_.jpg",
    "https://images-na.ssl-images-amazon.com/images/I/619rzmze5cL._AC_UL495_SR495,495_.jpg",
    "https://images-na.ssl-images-amazon.com/images/I/71C6VKCuzIL._AC_UL165_SR165,165_.jpg",
    "https://images-na.ssl-images-amazon.com/images/I/71C6VKCuzIL._AC_UL330_SR330,330_.jpg",
    "https://images-na.ssl-images-amazon.com/images/I/71C6VKCuzIL._AC_UL495_SR495,495_.jpg",
    "https://images-na.ssl-images-amazon.com/images/I/61+x0KV16VL._AC_UL165_SR165,165_.jpg",
    "https://images-na.ssl-images-amazon.com/images/I/61+x0KV16VL._AC_UL330_SR330,330_.jpg",
    "https://images-na.ssl-images-amazon.com/images/I/61+x0KV16VL._AC_UL495_SR495,495_.jpg",
    "https://images-na.ssl-images-amazon.com/images/I/61Ze79FUyTL._AC_UL165_SR165,165_.jpg",
    "https://images-na.ssl-images-amazon.com/images/I/61Ze79FUyTL._AC_UL330_SR330,330_.jpg",
    "https://images-na.ssl-images-amazon.com/images/I/61Ze79FUyTL._AC_UL495_SR495,495_.jpg",
    "https://images-na.ssl-images-amazon.com/images/I/510DzmplXvL._AC_UL165_SR165,165_.jpg",
    "https://images-na.ssl-images-amazon.com/images/I/510DzmplXvL._AC_UL330_SR330,330_.jpg",
    "https://images-na.ssl-images-amazon.com/images/I/510DzmplXvL._AC_UL495_SR495,495_.jpg",
    "https://images-na.ssl-images-amazon.com/images/I/51f4YvOwDXL._AC_UL165_SR165,165_.jpg",
    "https://images-na.ssl-images-amazon.com/images/I/51f4YvOwDXL._AC_UL330_SR330,330_.jpg",
    "https://images-na.ssl-images-amazon.com/images/I/51f4YvOwDXL._AC_UL495_SR495,495_.jpg"
  ],
  "video_urls": [],
  "platform": "amazon",
  "category": "necklace",
  "keyword": "silver pendant necklace",
  "scraped_at": "2026-03-08T13:34:09.725485",
  "download_stats": {
    "images_downloaded": 8,
    "videos_downloaded": 0,
    "images_skipped": 0
  }
}